setup.py
nodewox/thing/__init__.py
nodewox/thing/channel.py
nodewox/thing/cmd_thing.py
nodewox/thing/messenger.py
nodewox/thing/node.py
nodewox/thing/param.py
nodewox/thing/store.py
nodewox/thing/thing.py
nodewox_pything.egg-info/PKG-INFO
nodewox_pything.egg-info/SOURCES.txt
nodewox_pything.egg-info/dependency_links.txt
nodewox_pything.egg-info/entry_points.txt
nodewox_pything.egg-info/requires.txt
nodewox_pything.egg-info/top_level.txt